pySdk/__init__.py
pySdk/accessToken.py
pySdk/idToken.py
pySdk/renewToken.py
secuuthSdk/__init__.py
secuuthSdk/accessToken.py
secuuthSdk/idToken.py
secuuthSdk/renewToken.py
secuuthSecQurePythonSdk-2.8.dist-info/LICENSE
secuuthSecQurePythonSdk-2.8.dist-info/METADATA
secuuthSecQurePythonSdk-2.8.dist-info/WHEEL
secuuthSecQurePythonSdk-2.8.dist-info/top_level.txt
secuuthSecQurePythonSdk-2.8.dist-info/RECORD
